{"skeleton":{"hash":"lPOTPVIDcpjYVDJ2Owrh817nLhw","spine":"3.7.13-beta","width":0,"height":0,"images":"../output/","audio":""},"bones":[{"name":"root","rotation":-0.01},{"name":"bone","parent":"root","length":82.24,"rotation":0.38,"x":32.12,"y":29.64,"scaleX":0.295,"scaleY":0.295}],"slots":[{"name":"banana","bone":"bone","attachment":"slot"},{"name":"cherries-stem","bone":"bone","attachment":"cherries-stem"}],"skins":{"default":{"cherries-stem":{"cherries-stem":{"x":20.64,"y":38.31,"scaleX":1.25,"scaleY":1.172,"width":113,"height":131}}},"blue":{"banana":{"slot":{"name":"cherries","color":"0000ffff","x":-0.24,"y":-36.42,"scaleX":1.31,"scaleY":1.297,"rotation":-0.38,"width":135,"height":103}}},"brown":{"banana":{"slot":{"name":"cherries","color":"422400ff","x":-0.24,"y":-36.42,"scaleX":1.31,"scaleY":1.297,"rotation":-0.38,"width":135,"height":103}}},"cyan":{"banana":{"slot":{"name":"cherries","color":"00ffffff","x":-0.24,"y":-36.42,"scaleX":1.31,"scaleY":1.297,"rotation":-0.38,"width":135,"height":103}}},"dark-gray":{"banana":{"slot":{"name":"cherries","color":"2d2d2dff","x":-0.24,"y":-36.42,"scaleX":1.31,"scaleY":1.297,"rotation":-0.38,"width":135,"height":103}}},"gold":{"banana":{"slot":{"name":"cherries","color":"ffbf2fff","x":-0.24,"y":-36.42,"scaleX":1.31,"scaleY":1.297,"rotation":-0.38,"width":135,"height":103}}},"gray":{"banana":{"slot":{"name":"cherries","color":"8c8c8cff","x":-0.24,"y":-36.42,"scaleX":1.31,"scaleY":1.297,"rotation":-0.38,"width":135,"height":103}}},"green":{"banana":{"slot":{"name":"cherries","color":"00ff00ff","x":-0.24,"y":-36.42,"scaleX":1.31,"scaleY":1.297,"rotation":-0.38,"width":135,"height":103}}},"magenta":{"banana":{"slot":{"name":"cherries","color":"ff00ffff","x":-0.24,"y":-36.42,"scaleX":1.31,"scaleY":1.297,"rotation":-0.38,"width":135,"height":103}}},"orange":{"banana":{"slot":{"name":"cherries","color":"ff6a00ff","x":-0.24,"y":-36.42,"scaleX":1.31,"scaleY":1.297,"rotation":-0.38,"width":135,"height":103}}},"pink":{"banana":{"slot":{"name":"cherries","color":"fba5ffff","x":-0.24,"y":-36.42,"scaleX":1.31,"scaleY":1.297,"rotation":-0.38,"width":135,"height":103}}},"purple":{"banana":{"slot":{"name":"cherries","color":"7c00ffff","x":-0.24,"y":-36.42,"scaleX":1.31,"scaleY":1.297,"rotation":-0.38,"width":135,"height":103}}},"red":{"banana":{"slot":{"name":"cherries","color":"ff0000ff","x":-0.24,"y":-36.42,"scaleX":1.31,"scaleY":1.297,"rotation":-0.38,"width":135,"height":103}}},"white":{"banana":{"slot":{"name":"cherries","x":-0.24,"y":-36.42,"scaleX":1.31,"scaleY":1.297,"rotation":-0.38,"width":135,"height":103}}},"yellow":{"banana":{"slot":{"name":"cherries","color":"ffff00ff","x":-0.24,"y":-36.42,"scaleX":1.31,"scaleY":1.297,"rotation":-0.38,"width":135,"height":103}}}},"animations":{"animation":{}}}